funpaybotengine/__init__.py
funpaybotengine/base.py
funpaybotengine/loggers.py
funpaybotengine/utils.py
funpaybotengine/client/__init__.py
funpaybotengine/client/bot.py
funpaybotengine/client/default_hooks.py
funpaybotengine/client/session/__init__.py
funpaybotengine/client/session/aiohttp_session.py
funpaybotengine/client/session/base.py
funpaybotengine/client/session/http_methods.py
funpaybotengine/dispatching/__init__.py
funpaybotengine/dispatching/events/__init__.py
funpaybotengine/dispatching/events/base.py
funpaybotengine/dispatching/events/builtin_events.py
funpaybotengine/dispatching/filters/__init__.py
funpaybotengine/dispatching/filters/base.py
funpaybotengine/dispatching/filters/message_filters.py
funpaybotengine/dispatching/filters/order_filters.py
funpaybotengine/dispatching/handlers/__init__.py
funpaybotengine/dispatching/handlers/handler_manager.py
funpaybotengine/dispatching/routers/__init__.py
funpaybotengine/dispatching/routers/base.py
funpaybotengine/dispatching/routers/dispatcher.py
funpaybotengine/exceptions/__init__.py
funpaybotengine/exceptions/action_exceptions.py
funpaybotengine/exceptions/base.py
funpaybotengine/exceptions/bot_exceptions.py
funpaybotengine/exceptions/message_check_errors.py
funpaybotengine/exceptions/runner_exceptions.py
funpaybotengine/exceptions/session_exceptions.py
funpaybotengine/methods/__init__.py
funpaybotengine/methods/base.py
funpaybotengine/methods/calc_chips.py
funpaybotengine/methods/calc_lots.py
funpaybotengine/methods/check_banned.py
funpaybotengine/methods/delete_review.py
funpaybotengine/methods/get_2fa_status.py
funpaybotengine/methods/get_chat_history.py
funpaybotengine/methods/get_chat_page.py
funpaybotengine/methods/get_main_page.py
funpaybotengine/methods/get_my_chips_page.py
funpaybotengine/methods/get_my_offers_page.py
funpaybotengine/methods/get_offer_fields.py
funpaybotengine/methods/get_order_page.py
funpaybotengine/methods/get_profile_page.py
funpaybotengine/methods/get_purchases.py
funpaybotengine-0.1.12.dist-info/METADATA
funpaybotengine-0.1.12.dist-info/WHEEL
funpaybotengine-0.1.12.dist-info/RECORD
